pytest_proceed/__init__.py
pytest_proceed/pytest_proceed.py
pytest_proceed-0.1.5.dist-info/METADATA
pytest_proceed-0.1.5.dist-info/WHEEL
pytest_proceed-0.1.5.dist-info/entry_points.txt
pytest_proceed-0.1.5.dist-info/top_level.txt
pytest_proceed-0.1.5.dist-info/RECORD
