Metadata-Version: 2.1
Name: pytest-proceed
Version: 0.1.5
Requires-Python: >=3.6
Requires-Dist: pytest
Requires-Dist: argparse
